setup.py
wechatwork_send
wechat/__init__.py
wechat/config.py
wechat/main.py
wechat/options.py
wechat/modules/__init__.py
wechat/modules/configure.py
wechat/modules/message.py
wechat/modules/wechatwork.py
wechat/utils/__init__.py
wechat/utils/logs.py
wechat/utils/parsers.py
wechatwork_notify.egg-info/PKG-INFO
wechatwork_notify.egg-info/SOURCES.txt
wechatwork_notify.egg-info/dependency_links.txt
wechatwork_notify.egg-info/requires.txt
wechatwork_notify.egg-info/top_level.txt